{
  "generatedAt": "2026-06-08T01:18:58.532Z",
  "season": 2026,
  "record": {
    "holder": "Joe DiMaggio",
    "length": 56,
    "year": 1941,
    "team": "New York Yankees"
  },
  "milestones": [
    {
      "length": 20,
      "label": "20 games"
    },
    {
      "length": 30,
      "label": "30 games"
    },
    {
      "length": 40,
      "label": "40 games"
    },
    {
      "length": 44,
      "label": "44 — modern NL record (Pete Rose, 1978)"
    },
    {
      "length": 56,
      "label": "56 — DiMaggio's record"
    }
  ],
  "streaks": [
    {
      "rank": 1,
      "playerId": 808982,
      "name": "Jung Hoo Lee",
      "team": "SF",
      "teamName": "Giants",
      "streak": 15,
      "startDate": "2026-05-14",
      "lastHitDate": "2026-06-07",
      "lastGameDate": "2026-06-07",
      "gamesToRecord": 41,
      "nextMilestone": 20
    },
    {
      "rank": 2,
      "playerId": 680869,
      "name": "Zack Gelof",
      "team": "ATH",
      "teamName": "Athletics",
      "streak": 12,
      "startDate": "2026-05-25",
      "lastHitDate": "2026-06-07",
      "lastGameDate": "2026-06-07",
      "gamesToRecord": 44,
      "nextMilestone": 20
    },
    {
      "rank": 3,
      "playerId": 702284,
      "name": "Cole Young",
      "team": "SEA",
      "teamName": "Mariners",
      "streak": 10,
      "startDate": "2026-05-27",
      "lastHitDate": "2026-06-07",
      "lastGameDate": "2026-06-07",
      "gamesToRecord": 46,
      "nextMilestone": 20
    },
    {
      "rank": 4,
      "playerId": 805367,
      "name": "Chase Meidroth",
      "team": "CWS",
      "teamName": "White Sox",
      "streak": 9,
      "startDate": "2026-05-29",
      "lastHitDate": "2026-06-07",
      "lastGameDate": "2026-06-07",
      "gamesToRecord": 47,
      "nextMilestone": 20
    },
    {
      "rank": 5,
      "playerId": 676475,
      "name": "Alec Burleson",
      "team": "STL",
      "teamName": "Cardinals",
      "streak": 8,
      "startDate": "2026-05-30",
      "lastHitDate": "2026-06-07",
      "lastGameDate": "2026-06-07",
      "gamesToRecord": 48,
      "nextMilestone": 20
    },
    {
      "rank": 6,
      "playerId": 650333,
      "name": "Luis Arraez",
      "team": "SF",
      "teamName": "Giants",
      "streak": 8,
      "startDate": "2026-05-31",
      "lastHitDate": "2026-06-07",
      "lastGameDate": "2026-06-07",
      "gamesToRecord": 48,
      "nextMilestone": 20
    },
    {
      "rank": 7,
      "playerId": 605170,
      "name": "Victor Caratini",
      "team": "MIN",
      "teamName": "Twins",
      "streak": 8,
      "startDate": "2026-05-28",
      "lastHitDate": "2026-06-07",
      "lastGameDate": "2026-06-07",
      "gamesToRecord": 48,
      "nextMilestone": 20
    },
    {
      "rank": 8,
      "playerId": 668930,
      "name": "Brice Turang",
      "team": "MIL",
      "teamName": "Brewers",
      "streak": 7,
      "startDate": "2026-06-01",
      "lastHitDate": "2026-06-07",
      "lastGameDate": "2026-06-07",
      "gamesToRecord": 49,
      "nextMilestone": 20
    },
    {
      "rank": 9,
      "playerId": 805808,
      "name": "Kevin McGonigle",
      "team": "DET",
      "teamName": "Tigers",
      "streak": 7,
      "startDate": "2026-05-30",
      "lastHitDate": "2026-06-07",
      "lastGameDate": "2026-06-07",
      "gamesToRecord": 49,
      "nextMilestone": 20
    },
    {
      "rank": 10,
      "playerId": 687093,
      "name": "Vaughn Grissom",
      "team": "LAA",
      "teamName": "Angels",
      "streak": 7,
      "startDate": "2026-05-28",
      "lastHitDate": "2026-06-03",
      "lastGameDate": "2026-06-03",
      "gamesToRecord": 49,
      "nextMilestone": 20
    },
    {
      "rank": 11,
      "playerId": 669016,
      "name": "Brandon Marsh",
      "team": "PHI",
      "teamName": "Phillies",
      "streak": 6,
      "startDate": "2026-06-02",
      "lastHitDate": "2026-06-07",
      "lastGameDate": "2026-06-07",
      "gamesToRecord": 50,
      "nextMilestone": 20
    },
    {
      "rank": 12,
      "playerId": 663968,
      "name": "Jake Mangum",
      "team": "PIT",
      "teamName": "Pirates",
      "streak": 6,
      "startDate": "2026-05-30",
      "lastHitDate": "2026-06-07",
      "lastGameDate": "2026-06-07",
      "gamesToRecord": 50,
      "nextMilestone": 20
    },
    {
      "rank": 13,
      "playerId": 640902,
      "name": "Jhonny Pereda",
      "team": "SEA",
      "teamName": "Mariners",
      "streak": 6,
      "startDate": "2026-05-29",
      "lastHitDate": "2026-06-07",
      "lastGameDate": "2026-06-07",
      "gamesToRecord": 50,
      "nextMilestone": 20
    },
    {
      "rank": 14,
      "playerId": 672960,
      "name": "Kazuma Okamoto",
      "team": "TOR",
      "teamName": "Blue Jays",
      "streak": 6,
      "startDate": "2026-06-02",
      "lastHitDate": "2026-06-07",
      "lastGameDate": "2026-06-07",
      "gamesToRecord": 50,
      "nextMilestone": 20
    },
    {
      "rank": 15,
      "playerId": 678246,
      "name": "Miguel Vargas",
      "team": "CWS",
      "teamName": "White Sox",
      "streak": 6,
      "startDate": "2026-06-01",
      "lastHitDate": "2026-06-07",
      "lastGameDate": "2026-06-07",
      "gamesToRecord": 50,
      "nextMilestone": 20
    },
    {
      "rank": 16,
      "playerId": 670541,
      "name": "Yordan Alvarez",
      "team": "HOU",
      "teamName": "Astros",
      "streak": 6,
      "startDate": "2026-06-02",
      "lastHitDate": "2026-06-07",
      "lastGameDate": "2026-06-07",
      "gamesToRecord": 50,
      "nextMilestone": 20
    },
    {
      "rank": 17,
      "playerId": 805999,
      "name": "A.J. Ewing",
      "team": "NYM",
      "teamName": "Mets",
      "streak": 5,
      "startDate": "2026-06-02",
      "lastHitDate": "2026-06-07",
      "lastGameDate": "2026-06-07",
      "gamesToRecord": 51,
      "nextMilestone": 20
    },
    {
      "rank": 18,
      "playerId": 664761,
      "name": "Alec Bohm",
      "team": "PHI",
      "teamName": "Phillies",
      "streak": 5,
      "startDate": "2026-06-03",
      "lastHitDate": "2026-06-07",
      "lastGameDate": "2026-06-07",
      "gamesToRecord": 51,
      "nextMilestone": 20
    },
    {
      "rank": 19,
      "playerId": 694362,
      "name": "Blake Dunn",
      "team": "CIN",
      "teamName": "Reds",
      "streak": 5,
      "startDate": "2026-06-02",
      "lastHitDate": "2026-06-07",
      "lastGameDate": "2026-06-07",
      "gamesToRecord": 51,
      "nextMilestone": 20
    },
    {
      "rank": 20,
      "playerId": 681715,
      "name": "Heriberto Hernández",
      "team": "MIA",
      "teamName": "Marlins",
      "streak": 5,
      "startDate": "2026-06-01",
      "lastHitDate": "2026-06-07",
      "lastGameDate": "2026-06-07",
      "gamesToRecord": 51,
      "nextMilestone": 20
    },
    {
      "rank": 21,
      "playerId": 691023,
      "name": "Jordan Walker",
      "team": "STL",
      "teamName": "Cardinals",
      "streak": 5,
      "startDate": "2026-06-02",
      "lastHitDate": "2026-06-07",
      "lastGameDate": "2026-06-07",
      "gamesToRecord": 51,
      "nextMilestone": 20
    },
    {
      "rank": 22,
      "playerId": 673962,
      "name": "Josh Jung",
      "team": "TEX",
      "teamName": "Rangers",
      "streak": 5,
      "startDate": "2026-06-02",
      "lastHitDate": "2026-06-07",
      "lastGameDate": "2026-06-07",
      "gamesToRecord": 51,
      "nextMilestone": 20
    },
    {
      "rank": 23,
      "playerId": 543309,
      "name": "Kyle Higashioka",
      "team": "TEX",
      "teamName": "Rangers",
      "streak": 5,
      "startDate": "2026-05-31",
      "lastHitDate": "2026-06-06",
      "lastGameDate": "2026-06-06",
      "gamesToRecord": 51,
      "nextMilestone": 20
    },
    {
      "rank": 24,
      "playerId": 655316,
      "name": "Andruw Monasterio",
      "team": "BOS",
      "teamName": "Red Sox",
      "streak": 4,
      "startDate": "2026-05-30",
      "lastHitDate": "2026-06-07",
      "lastGameDate": "2026-06-07",
      "gamesToRecord": 52,
      "nextMilestone": 20
    },
    {
      "rank": 25,
      "playerId": 666182,
      "name": "Bo Bichette",
      "team": "NYM",
      "teamName": "Mets",
      "streak": 4,
      "startDate": "2026-06-03",
      "lastHitDate": "2026-06-07",
      "lastGameDate": "2026-06-07",
      "gamesToRecord": 52,
      "nextMilestone": 20
    }
  ]
}
